lazuardy_anfis/__init__.py
lazuardy_anfis/anfis.py
lazuardy_anfis/anfis_gpu.py
lazuardy_anfis/membershipfunction.py
lazuardy_anfis/tests.py
lazuardy_anfis/tests_gpu.py
lazuardy_anfis-0.0.8.dist-info/LICENSE
lazuardy_anfis-0.0.8.dist-info/METADATA
lazuardy_anfis-0.0.8.dist-info/WHEEL
lazuardy_anfis-0.0.8.dist-info/top_level.txt
lazuardy_anfis-0.0.8.dist-info/RECORD
