Metadata-Version: 2.1
Name: lazuardy-anfis
Version: 0.0.8
Summary: Adaptive Neuro Fuzzy Inference System Implementation in Python.
Home-page: https://github.com/lazuardy-tech/anfis
Download-URL: https://github.com/lazuardy-tech/anfis/releases
Author: Lazuardy
Author-email: contact@lazuardy.tech
License: MIT
Keywords: anfis,fuzzy logic,neural networks,fnn,lazuardy,lazuardy anfis
Classifier: Development Status :: 3 - Alpha
Classifier: Intended Audience :: Developers
Classifier: Intended Audience :: Science/Research
Classifier: License :: OSI Approved :: MIT License
Classifier: Programming Language :: Python :: 2
Classifier: Programming Language :: Python :: 2.6
Classifier: Programming Language :: Python :: 2.7
Classifier: Programming Language :: Python :: 3
License-File: LICENSE
Requires-Dist: cycler ==0.11.0
Requires-Dist: fonttools ==4.38.0
Requires-Dist: joblib ==1.3.2
Requires-Dist: kiwisolver ==1.4.5
Requires-Dist: matplotlib ==3.5.3
Requires-Dist: numpy ==1.21.6
Requires-Dist: packaging ==24.0
Requires-Dist: pandas ==1.3.5
Requires-Dist: Pillow ==9.5.0
Requires-Dist: pyparsing ==3.1.4
Requires-Dist: python-dateutil ==2.9.0.post0
Requires-Dist: pytz ==2024.2
Requires-Dist: scikit-fuzzy ==0.5.0
Requires-Dist: scikit-learn ==1.0.2
Requires-Dist: scipy ==1.7.3
Requires-Dist: six ==1.16.0
Requires-Dist: threadpoolctl ==3.1.0
Requires-Dist: torch ==1.13.1
Requires-Dist: typing-extensions ==4.7.1
